[
null,
{"id":1,"animationId":0,"damage":{"critical":true,"elementId":-1,"formula":"a.atk * 2","type":1,"variance":20},"description":"","effects":[{"code":21,"dataId":0,"value1":1,"value2":0}],"hitType":1,"iconIndex":327,"message1":" ¡ataca!","message2":"","mpCost":0,"name":"Attack","note":"<Target Action>\nmotion missile: user\njump user: 40%\nmove user: target, front, 15\nwait for movement\nwait: 20\nmotion thrust: user\nmotion wait: user\nmotion swing: user\naction animation: target\naction effect: target\n</Target Action>","occasion":1,"repeats":1,"requiredWtypeId1":0,"requiredWtypeId2":0,"scope":1,"speed":0,"stypeId":0,"successRate":100,"tpCost":0,"tpGain":10},
{"id":2,"animationId":0,"damage":{"critical":false,"elementId":0,"formula":"0","type":0,"variance":20},"description":"","effects":[{"code":21,"dataId":2,"value1":1,"value2":0}],"hitType":0,"iconIndex":81,"message1":" se protege.","message2":"","mpCost":0,"name":"Defense","note":"La habilidad #2 se utilizará\nal seleccionar el comando Defensa.","occasion":1,"repeats":1,"requiredWtypeId1":0,"requiredWtypeId2":0,"scope":11,"speed":2000,"stypeId":0,"successRate":100,"tpCost":0,"tpGain":10},
{"id":3,"animationId":-1,"damage":{"critical":false,"elementId":-1,"formula":"a.atk * 2","type":1,"variance":20},"description":"","effects":[{"code":21,"dataId":0,"value1":1,"value2":0}],"hitType":1,"iconIndex":334,"message1":" ¡ataca!","message2":"","mpCost":0,"name":"Ataque dual","note":"<Cooldown: 7>\n<Cast Animation: 0>\n<Armor Penetration: 20%>","occasion":1,"repeats":2,"requiredWtypeId1":0,"requiredWtypeId2":0,"scope":1,"speed":0,"stypeId":0,"successRate":100,"tpCost":0,"tpGain":5},
{"id":4,"animationId":-1,"damage":{"critical":true,"elementId":-1,"formula":"a.atk * 3","type":1,"variance":20},"description":"","effects":[{"code":21,"dataId":0,"value1":1,"value2":0}],"hitType":1,"iconIndex":334,"message1":" ¡ataca!","message2":"","mpCost":0,"name":"Ataque doble","note":"<Cooldown: 4>\n<Armor Penetration: 20%>","occasion":1,"repeats":1,"requiredWtypeId1":0,"requiredWtypeId2":0,"scope":4,"speed":0,"stypeId":0,"successRate":100,"tpCost":0,"tpGain":5},
{"id":5,"animationId":0,"damage":{"critical":false,"elementId":-1,"formula":"a.atk * 4","type":1,"variance":20},"description":"","effects":[{"code":21,"dataId":0,"value1":1,"value2":0}],"hitType":1,"iconIndex":334,"message1":" ¡ataca!","message2":"","mpCost":0,"name":"Ataque triple","note":"<Cooldown: 4>\n<Armor Penetration: 15%>\n<HP Life Steal: 45%>\n<Cast Animation: 0>","occasion":1,"repeats":1,"requiredWtypeId1":0,"requiredWtypeId2":0,"scope":5,"speed":0,"stypeId":0,"successRate":100,"tpCost":0,"tpGain":4},
{"id":6,"animationId":0,"damage":{"critical":false,"elementId":0,"formula":"0","type":0,"variance":20},"description":"","effects":[{"code":41,"dataId":0,"value1":0,"value2":0}],"hitType":0,"iconIndex":330,"message1":" huye.","message2":"","mpCost":0,"name":"Huida","note":"","occasion":1,"repeats":1,"requiredWtypeId1":0,"requiredWtypeId2":0,"scope":11,"speed":0,"stypeId":0,"successRate":100,"tpCost":0,"tpGain":0},
{"id":7,"animationId":0,"damage":{"critical":false,"elementId":0,"formula":"0","type":0,"variance":20},"description":"","effects":[],"hitType":0,"iconIndex":81,"message1":" espera.","message2":"","mpCost":0,"name":"Esperar","note":"","occasion":1,"repeats":1,"requiredWtypeId1":0,"requiredWtypeId2":0,"scope":0,"speed":0,"stypeId":0,"successRate":100,"tpCost":0,"tpGain":10},
{"id":8,"animationId":0,"damage":{"critical":false,"elementId":0,"formula":"0","type":0,"variance":20},"description":"","effects":[],"hitType":0,"iconIndex":0,"message1":"","message2":"","mpCost":0,"name":"","note":"","occasion":0,"repeats":1,"requiredWtypeId1":0,"requiredWtypeId2":0,"scope":1,"speed":0,"stypeId":1,"successRate":100,"tpCost":0,"tpGain":0},
{"id":9,"animationId":50,"damage":{"critical":false,"elementId":0,"formula":"0","type":0,"variance":20},"description":"Revive your ally with 25% of HP.","effects":[{"code":22,"dataId":1,"value1":1,"value2":0},{"code":11,"dataId":0,"value1":0.25,"value2":0}],"hitType":0,"iconIndex":320,"message1":"","message2":"","mpCost":100,"name":"Revive","note":"<Cooldown: 10>","occasion":0,"repeats":1,"requiredWtypeId1":0,"requiredWtypeId2":0,"scope":9,"speed":0,"stypeId":1,"successRate":100,"tpCost":0,"tpGain":0},
{"id":10,"animationId":0,"damage":{"critical":false,"elementId":0,"formula":"0","type":0,"variance":20},"description":"[I.Cast] You try to distract the enemy.\n[75% Attack down] [5% Stun] [5% Confusion] [50% Love] [I.C]","effects":[{"code":21,"dataId":26,"value1":0.75,"value2":0},{"code":21,"dataId":17,"value1":0.05,"value2":0},{"code":21,"dataId":8,"value1":0.05,"value2":0},{"code":21,"dataId":9,"value1":0.5,"value2":0}],"hitType":0,"iconIndex":298,"message1":"","message2":"","mpCost":30,"name":"Harem no jutsu","note":"<Cooldown: 7>\n<Instant Cast>\n\n<Hide if Learned Skill: 94>\n\n<Whole Action>\nHIDE BATTLE HUD\nmotion chant: user\ncommon event: 20\nanimation 33: user\nwait for animation\naction effect: target\nSHOW BATTLE HUD\n</Whole action>","occasion":1,"repeats":1,"requiredWtypeId1":0,"requiredWtypeId2":0,"scope":2,"speed":0,"stypeId":1,"successRate":100,"tpCost":0,"tpGain":0},
{"id":11,"animationId":0,"damage":{"critical":false,"elementId":0,"formula":"a.atk * 5","type":1,"variance":20},"description":"[I.C] You need to have kunai in your inventory.\n[30% Bleed] [Strengh scale] [I.C]","effects":[{"code":21,"dataId":22,"value1":0.3,"value2":0}],"hitType":1,"iconIndex":347,"message1":"","message2":"","mpCost":0,"name":"KunaiThrow","note":"<Item Cost: 1 Kunais>\n<Cooldown: 3>\n\n<Instant Cast>","occasion":0,"repeats":1,"requiredWtypeId1":0,"requiredWtypeId2":0,"scope":1,"speed":0,"stypeId":1,"successRate":100,"tpCost":0,"tpGain":0},
{"id":12,"animationId":0,"damage":{"critical":false,"elementId":0,"formula":"a.atk * 3","type":1,"variance":20},"description":"You damage all opponents with clones.\n[Strengh scale]","effects":[],"hitType":1,"iconIndex":293,"message1":"","message2":"","mpCost":30,"name":"Clone attack","note":"<Cooldown: 5>\n<Cast Animation: 0>\n\n<Target action>\nmotion chant: user\naction effect: target\n</Target action>","occasion":0,"repeats":1,"requiredWtypeId1":0,"requiredWtypeId2":0,"scope":2,"speed":0,"stypeId":1,"successRate":100,"tpCost":0,"tpGain":0},
{"id":13,"animationId":0,"damage":{"critical":true,"elementId":0,"formula":"a.mat * 6","type":1,"variance":35},"description":"A powerful technique taught to you by Jiraiya.\n[CHK.F SCALE]","effects":[],"hitType":2,"iconIndex":336,"message1":"","message2":"","mpCost":0,"name":"Rasengan","note":"<Cooldown: 6>\n<Armor Penetration: 15%>\n<MP Cost: 40%>\n<Action Cutin>\n\n<Target action>\nHIDE BATTLE HUD\nmotion skill: user\nwait for animation\nmotion abnormal: user\nwait for animation\ncamera focus: user\nzoom: 200%, 60\nwait for zoom\nreset camera: 1\nreset zoom: 1\ncommon event: 14\ncamera focus: user\nmotion missile: user\nmove user: target, front, 1\nwait for animation\nshake screen: 9, 9, 10\naction effect: target\naction effect: target\nanimation 92: target\nreset camera: 20\nreset zoom: 20\nSHOW BATTLE HUD\n</Target action>","occasion":1,"repeats":1,"requiredWtypeId1":0,"requiredWtypeId2":0,"scope":1,"speed":-2000,"stypeId":1,"successRate":100,"tpCost":0,"tpGain":0},
{"id":14,"animationId":0,"damage":{"critical":false,"elementId":0,"formula":"a.atk * 4","type":1,"variance":35},"description":"You damage a single opponent and acquire multiple hits.\n[Strengh scale] [x3 Basic attack]","effects":[],"hitType":1,"iconIndex":349,"message1":"","message2":"","mpCost":35,"name":"Shuriken Kage Bunshin no Jutsu","note":"<Cooldown: 5>\n\n<Action Cutin>\n<Target action>\nmotion chant: user\naction effect: target\nanimation 6: target\nadd state 12: user\n</Target action>\n","occasion":1,"repeats":1,"requiredWtypeId1":0,"requiredWtypeId2":0,"scope":1,"speed":0,"stypeId":1,"successRate":100,"tpCost":0,"tpGain":0},
{"id":15,"animationId":-1,"damage":{"critical":true,"elementId":-1,"formula":"a.atk * 2","type":1,"variance":20},"description":"","effects":[{"code":21,"dataId":0,"value1":1,"value2":0}],"hitType":1,"iconIndex":348,"message1":" ¡ataca!","message2":"","mpCost":0,"name":"Attack R","note":"<Cast Animation: 0>\n<Armor Penetration: 15%>\n<ATB Interrupt>\n\n<Target Action>\nmotion chant: user\naction effect: target\n</Target Action>","occasion":1,"repeats":1,"requiredWtypeId1":0,"requiredWtypeId2":0,"scope":1,"speed":0,"stypeId":0,"successRate":100,"tpCost":0,"tpGain":10},
{"id":16,"animationId":41,"damage":{"critical":false,"elementId":0,"formula":"a.mat * 1.3","type":3,"variance":20},"description":"Recover HP to the selected member.\n[CHK. F. Scale]","effects":[],"hitType":0,"iconIndex":321,"message1":" ¡lanza %1!","message2":"","mpCost":12,"name":"Heal","note":"<Cooldown: 3>\n<MP Cost: 15%>\n<Target action>\nmotion chant: user\naction effect: target\n</Target action>","occasion":0,"repeats":1,"requiredWtypeId1":0,"requiredWtypeId2":0,"scope":7,"speed":0,"stypeId":1,"successRate":100,"tpCost":0,"tpGain":10},
{"id":17,"animationId":53,"damage":{"critical":false,"elementId":0,"formula":"0","type":0,"variance":20},"description":"Anti debuff \n[I.C]","effects":[],"hitType":0,"iconIndex":322,"message1":"","message2":"","mpCost":0,"name":"Cover","note":"<Cooldown: 8>\n\n<Instant Cast>\n\n<User Barrier 2 turns: +60>\n\n<MP Cost: 30%>\n\n<Whole action>\nadd state 15: user\n</Whole action>","occasion":1,"repeats":1,"requiredWtypeId1":0,"requiredWtypeId2":0,"scope":11,"speed":0,"stypeId":1,"successRate":100,"tpCost":0,"tpGain":0},
{"id":18,"animationId":0,"damage":{"critical":false,"elementId":0,"formula":"a.hp * 1.5","type":1,"variance":35},"description":"A very powerful punch that causes area damage to enemies.\n[15% Silence] [15% Confusion] [Healing red.] [HP SCALE]","effects":[{"code":21,"dataId":17,"value1":0.25,"value2":0},{"code":21,"dataId":6,"value1":0.25,"value2":0},{"code":21,"dataId":8,"value1":0.25,"value2":0},{"code":21,"dataId":46,"value1":1,"value2":0}],"hitType":1,"iconIndex":323,"message1":"","message2":"","mpCost":30,"name":"Deadly punch","note":"<Cooldown: 6>\n\n<Action Cutin>\n\n<Whole Action>\nHIDE BATTLE HUD\nmotion guard: user\ncommon event: 12\nanimation 89: target\nadd state 19, 28: user\nSHOW BATTLE HUD\n</Whole Action>\n","occasion":1,"repeats":1,"requiredWtypeId1":0,"requiredWtypeId2":0,"scope":2,"speed":0,"stypeId":1,"successRate":100,"tpCost":0,"tpGain":0},
{"id":19,"animationId":41,"damage":{"critical":false,"elementId":0,"formula":"a.mat * 0.3","type":3,"variance":20},"description":"Recover HP to the selected member for 3 turns.\n[CHK. F. Scale]","effects":[{"code":21,"dataId":16,"value1":1,"value2":0}],"hitType":2,"iconIndex":324,"message1":"","message2":"","mpCost":25,"name":"Regeneration","note":"<Cooldown: 3>\n\n<Target action>\nmotion chant: user\nwait for animation\naction effect: target\n</Target action>\n","occasion":1,"repeats":1,"requiredWtypeId1":0,"requiredWtypeId2":0,"scope":7,"speed":0,"stypeId":1,"successRate":100,"tpCost":0,"tpGain":0},
{"id":20,"animationId":0,"damage":{"critical":false,"elementId":-1,"formula":"a.atk * 3","type":1,"variance":20},"description":"","effects":[{"code":21,"dataId":0,"value1":1,"value2":0},{"code":21,"dataId":24,"value1":0.35,"value2":0}],"hitType":1,"iconIndex":291,"message1":"","message2":"","mpCost":0,"name":"Serpent's sword","note":"<Cast Animation: 0>\n<Action Cutin>\n<Cooldown: 6>\n<Target action>\nmotion chant: user\nanimation 23: target\naction effect: target\nwait for animation\naction effect: target\nanimation 24: target\naction effect: target\nwait for animation\naction effect: target\n</Target action>","occasion":1,"repeats":1,"requiredWtypeId1":0,"requiredWtypeId2":0,"scope":2,"speed":0,"stypeId":1,"successRate":100,"tpCost":0,"tpGain":0},
{"id":21,"animationId":0,"damage":{"critical":true,"elementId":-1,"formula":"a.atk * 1.4","type":1,"variance":20},"description":"","effects":[{"code":21,"dataId":0,"value1":1,"value2":0}],"hitType":1,"iconIndex":294,"message1":" ¡ataca!","message2":"","mpCost":0,"name":"Kusanagi","note":"<Armor Penetration: 10%>\n<Target Action>\nmotion missile: user\nwait for animation\nmotion swing: user\nwait for animation\nanimation 6: target\nwait for animation\naction effect: target\naction effect: target\n</Target Action>","occasion":1,"repeats":1,"requiredWtypeId1":0,"requiredWtypeId2":0,"scope":5,"speed":0,"stypeId":0,"successRate":100,"tpCost":0,"tpGain":10},
{"id":22,"animationId":51,"damage":{"critical":false,"elementId":0,"formula":"0","type":0,"variance":20},"description":"","effects":[{"code":21,"dataId":50,"value1":1,"value2":0}],"hitType":0,"iconIndex":331,"message1":"","message2":"","mpCost":0,"name":"Transmutation","note":"<Cooldown: 5>\n<Instant Cast>\n<Target Action>\naction effect: user\n</Target Action>","occasion":0,"repeats":1,"requiredWtypeId1":0,"requiredWtypeId2":0,"scope":11,"speed":0,"stypeId":1,"successRate":100,"tpCost":0,"tpGain":0},
{"id":23,"animationId":0,"damage":{"critical":false,"elementId":0,"formula":"","type":0,"variance":20},"description":"","effects":[{"code":21,"dataId":21,"value1":1,"value2":0},{"code":21,"dataId":10,"value1":1,"value2":0}],"hitType":0,"iconIndex":290,"message1":"","message2":"","mpCost":0,"name":"Kill intent","note":"<Cooldown: 7>\n<Instant Cast>\n\n<Action Cutin>\n\n<Whole action>\nHIDE BATTLE HUD\ncommon event: 15\nSHOW BATTLE HUD\n</Whole action>","occasion":1,"repeats":1,"requiredWtypeId1":0,"requiredWtypeId2":0,"scope":2,"speed":0,"stypeId":1,"successRate":100,"tpCost":0,"tpGain":0},
{"id":24,"animationId":52,"damage":{"critical":false,"elementId":0,"formula":"0","type":0,"variance":20},"description":"","effects":[],"hitType":0,"iconIndex":289,"message1":"","message2":"","mpCost":0,"name":"Snake Summon","note":"<Cooldown: 9>\n\n<Target action>\ncommon event: 13\n</Target action>\n","occasion":0,"repeats":1,"requiredWtypeId1":0,"requiredWtypeId2":0,"scope":1,"speed":0,"stypeId":1,"successRate":100,"tpCost":0,"tpGain":0},
{"id":25,"animationId":51,"damage":{"critical":false,"elementId":0,"formula":"0","type":0,"variance":20},"description":"Increases the attack and defense of the party (small).\n[I.C]","effects":[{"code":21,"dataId":33,"value1":1,"value2":0},{"code":21,"dataId":34,"value1":1,"value2":0}],"hitType":0,"iconIndex":326,"message1":"","message2":"","mpCost":15,"name":"Buff","note":"<Cooldown: 4>\n<Instant Cast>\n\n<Hide if Learned Skill: 69>","occasion":0,"repeats":1,"requiredWtypeId1":0,"requiredWtypeId2":0,"scope":8,"speed":0,"stypeId":1,"successRate":100,"tpCost":0,"tpGain":0},
{"id":26,"animationId":0,"damage":{"critical":false,"elementId":0,"formula":"0","type":0,"variance":20},"description":"The kyubi gives you some of its strength for 3 turns.\n[I.C] [COST HP% 20]","effects":[],"hitType":0,"iconIndex":296,"message1":"","message2":"","mpCost":0,"name":"Kyubi","note":"<After battle Cooldown: -99>\n<Cooldown: 7>\n<Instant Cast>\n<HP Cost: 10%>\n\n<target action>\nmotion chant: user\nwait for animation\nadd state 13: user\nanimation 119: user\n</target action>","occasion":1,"repeats":1,"requiredWtypeId1":0,"requiredWtypeId2":0,"scope":0,"speed":0,"stypeId":1,"successRate":100,"tpCost":0,"tpGain":0},
{"id":27,"animationId":51,"damage":{"critical":false,"elementId":0,"formula":"0","type":0,"variance":20},"description":"","effects":[{"code":31,"dataId":6,"value1":30,"value2":0}],"hitType":0,"iconIndex":332,"message1":"","message2":"","mpCost":0,"name":"Buff speed","note":"<Instant cast>\n<Cooldown: 6>","occasion":0,"repeats":1,"requiredWtypeId1":0,"requiredWtypeId2":0,"scope":7,"speed":0,"stypeId":1,"successRate":100,"tpCost":0,"tpGain":0},
{"id":28,"animationId":43,"damage":{"critical":false,"elementId":0,"formula":"a.mat * 1","type":3,"variance":20},"description":"Heals all members of the team\n[CHK. F. Scale]","effects":[],"hitType":0,"iconIndex":335,"message1":" ¡lanza %1!","message2":"","mpCost":30,"name":"Party heal","note":"<Cooldown: 5>\n","occasion":0,"repeats":1,"requiredWtypeId1":0,"requiredWtypeId2":0,"scope":8,"speed":0,"stypeId":1,"successRate":100,"tpCost":0,"tpGain":10},
{"id":29,"animationId":52,"damage":{"critical":false,"elementId":0,"formula":"0","type":0,"variance":20},"description":"[Instant Cast]\nRecover 75% of your chakra","effects":[{"code":12,"dataId":0,"value1":0.75,"value2":0}],"hitType":0,"iconIndex":328,"message1":"","message2":"","mpCost":0,"name":"Recover chakra","note":"<Cooldown: 15>\n<Action cutin>\n<Instant Cast>\n<Warmup: 1>\n<Target action>\nmotion chant: user\naction effect: user\n</Target action>","occasion":0,"repeats":1,"requiredWtypeId1":0,"requiredWtypeId2":0,"scope":11,"speed":-2000,"stypeId":1,"successRate":100,"tpCost":0,"tpGain":0},
{"id":30,"animationId":52,"damage":{"critical":false,"elementId":0,"formula":"0","type":0,"variance":20},"description":"Removes all debuffs from your ally.\n[I.C]","effects":[{"code":22,"dataId":21,"value1":1,"value2":0},{"code":22,"dataId":24,"value1":1,"value2":0},{"code":21,"dataId":28,"value1":1,"value2":0},{"code":22,"dataId":10,"value1":1,"value2":0},{"code":22,"dataId":23,"value1":1,"value2":0},{"code":22,"dataId":22,"value1":1,"value2":0},{"code":22,"dataId":24,"value1":1,"value2":0}],"hitType":0,"iconIndex":337,"message1":"","message2":"","mpCost":80,"name":"Gotcha","note":"<Cooldown: 6>\n<Instant Cast>\n","occasion":0,"repeats":1,"requiredWtypeId1":0,"requiredWtypeId2":0,"scope":7,"speed":0,"stypeId":1,"successRate":100,"tpCost":0,"tpGain":0},
{"id":31,"animationId":0,"damage":{"critical":false,"elementId":0,"formula":"a.def * 4","type":1,"variance":20},"description":"Strong hit directly to the face.\n[50% Stun] [35% Armor pen] [30% Crit chance] [DEF SCALE]","effects":[{"code":21,"dataId":17,"value1":0.5,"value2":0}],"hitType":1,"iconIndex":341,"message1":"","message2":"","mpCost":30,"name":"Heavy punch","note":"<Cooldown: 5>\n<Critical Rate: 30%>\n<Armor Penetration: 35%>\n","occasion":0,"repeats":1,"requiredWtypeId1":0,"requiredWtypeId2":0,"scope":1,"speed":0,"stypeId":1,"successRate":100,"tpCost":0,"tpGain":0},
{"id":32,"animationId":0,"damage":{"critical":false,"elementId":0,"formula":"a.atk * 3","type":1,"variance":20},"description":"","effects":[{"code":21,"dataId":22,"value1":1,"value2":0}],"hitType":1,"iconIndex":342,"message1":"","message2":"","mpCost":0,"name":"Bleed area","note":"<Cooldown: 3>","occasion":0,"repeats":1,"requiredWtypeId1":0,"requiredWtypeId2":0,"scope":2,"speed":0,"stypeId":1,"successRate":100,"tpCost":0,"tpGain":0},
{"id":33,"animationId":53,"damage":{"critical":false,"elementId":0,"formula":"0","type":0,"variance":20},"description":"Put 80 points of barrier.","effects":[],"hitType":0,"iconIndex":325,"message1":"","message2":"","mpCost":22,"name":"Weak barrier","note":"<Cooldown: 5>\n<Target Barrier: +80>\n\n<Hide if Learned Skill: 67>","occasion":0,"repeats":1,"requiredWtypeId1":0,"requiredWtypeId2":0,"scope":7,"speed":0,"stypeId":1,"successRate":100,"tpCost":0,"tpGain":0},
{"id":34,"animationId":0,"damage":{"critical":false,"elementId":0,"formula":"a.agi * 15","type":1,"variance":20},"description":"You open the third door with Lee (5 Turns)\nincreasing your stats and losing 20% of life per turn.","effects":[{"code":22,"dataId":4,"value1":1,"value2":0},{"code":22,"dataId":5,"value1":1,"value2":0},{"code":22,"dataId":6,"value1":1,"value2":0},{"code":22,"dataId":23,"value1":1,"value2":0},{"code":22,"dataId":24,"value1":1,"value2":0}],"hitType":1,"iconIndex":389,"message1":"","message2":"","mpCost":0,"name":"Third Gate Open","note":"<After battle Cooldown: -99>\n<Armor Penetration: 20%>\n<Cooldown: 10>\n<Instant Cast>\n<HP Cost: 35%>\n<Action Cutin>\n\n<Target action>\nHIDE BATTLE HUD\nmotion guard: user\nwait for animation\ncommon event: 46\nmotion swing: user\nmove user: target, front, 1\nwait for animation\nshake screen: 9, 9, 10\naction effect: target\naction effect: target\nanimation 92: target\nadd state 35: user\nSHOW BATTLE HUD\n</Target action>","occasion":1,"repeats":1,"requiredWtypeId1":0,"requiredWtypeId2":0,"scope":1,"speed":0,"stypeId":1,"successRate":100,"tpCost":0,"tpGain":0},
{"id":35,"animationId":0,"damage":{"critical":true,"elementId":0,"formula":"a.agi * 5","type":1,"variance":20},"description":"Area damage [Damage scales with Speed]","effects":[],"hitType":1,"iconIndex":386,"message1":"","message2":"","mpCost":0,"name":"Speed deployment","note":"<Cooldown: 5>\n<Cast Animation: 0>\n<HP Cost: 20%>\n\n\n<Target action>\nmotion chant: user\naction effect: target\n</Target action>","occasion":1,"repeats":1,"requiredWtypeId1":0,"requiredWtypeId2":0,"scope":2,"speed":0,"stypeId":1,"successRate":100,"tpCost":0,"tpGain":0},
{"id":36,"animationId":0,"damage":{"critical":false,"elementId":0,"formula":"a.agi * 10","type":1,"variance":20},"description":"High single damage [Damage scales with Speed]","effects":[],"hitType":1,"iconIndex":384,"message1":"","message2":"","mpCost":0,"name":"Hidden Lotus","note":"<Cooldown: 6>\n<Cast Animation: 0>\n<Armor Penetration: 50%>\n<HP Cost: 30%>\n\n<Target Action>\nmotion guard: user\nmove user: target, middle, 3\nwait for movement\nmotion missile: user\nwait for animation\naction effect: target\nwait: 3\n</Target Action>","occasion":1,"repeats":1,"requiredWtypeId1":0,"requiredWtypeId2":0,"scope":1,"speed":0,"stypeId":1,"successRate":100,"tpCost":0,"tpGain":0},
{"id":37,"animationId":0,"damage":{"critical":false,"elementId":0,"formula":"0","type":0,"variance":20},"description":"Lee has an unbreakable iron will you recover 100% of \nyour HP (available only once per battle).","effects":[{"code":11,"dataId":0,"value1":1,"value2":350},{"code":22,"dataId":10,"value1":1,"value2":0},{"code":22,"dataId":38,"value1":1,"value2":0},{"code":22,"dataId":23,"value1":1,"value2":0},{"code":22,"dataId":22,"value1":1,"value2":0},{"code":22,"dataId":47,"value1":1,"value2":0}],"hitType":0,"iconIndex":385,"message1":"","message2":"","mpCost":0,"name":"Iron will","note":"<Cooldown: 99>\n<Instant Cast>\n<After battle Cooldown: -99>\n","occasion":1,"repeats":1,"requiredWtypeId1":0,"requiredWtypeId2":0,"scope":11,"speed":0,"stypeId":1,"successRate":100,"tpCost":0,"tpGain":0},
{"id":38,"animationId":0,"damage":{"critical":true,"elementId":0,"formula":"a.atk * 3","type":1,"variance":40},"description":"","effects":[{"code":21,"dataId":0,"value1":1,"value2":0}],"hitType":1,"iconIndex":77,"message1":"","message2":"","mpCost":0,"name":"Attack r","note":"<HP Life Steal: 30%>\n<Target Action>\nmove user: target, front, 1\nwait for movement\nmotion swing: user\nwait for animation\naction effect: target\nwait: 3\nmove user: target, back, 3\nwait for movement\nmotion abnormal: user\nwait for animation\naction effect: target\nwait: 5\nmove user: target, center, 3\nwait for movement\nmotion missile: user\nwait for animation\naction effect: target\nwait: 8\n</Target Action>","occasion":1,"repeats":1,"requiredWtypeId1":0,"requiredWtypeId2":0,"scope":1,"speed":0,"stypeId":0,"successRate":100,"tpCost":0,"tpGain":0},
{"id":39,"animationId":0,"damage":{"critical":false,"elementId":0,"formula":"0","type":0,"variance":20},"description":"[I.C] Recover 50% and increases 50% crit chance, and speed.\n[You need sake in your inventory]","effects":[{"code":21,"dataId":36,"value1":1,"value2":0},{"code":11,"dataId":0,"value1":0.25,"value2":0},{"code":21,"dataId":32,"value1":1,"value2":0},{"code":22,"dataId":10,"value1":1,"value2":0},{"code":22,"dataId":38,"value1":1,"value2":0},{"code":22,"dataId":23,"value1":1,"value2":0},{"code":22,"dataId":22,"value1":1,"value2":0},{"code":22,"dataId":47,"value1":1,"value2":0}],"hitType":0,"iconIndex":387,"message1":"","message2":"","mpCost":0,"name":"Sake","note":"<Item Cost: 1 Sake>\n<Cooldown: 7>\n\n<Instant Cast>","occasion":0,"repeats":1,"requiredWtypeId1":0,"requiredWtypeId2":0,"scope":11,"speed":0,"stypeId":1,"successRate":100,"tpCost":0,"tpGain":0},
{"id":40,"animationId":0,"damage":{"critical":false,"elementId":0,"formula":"0","type":0,"variance":20},"description":"You provoke the enemies, 55% of counterattack, \n35% evasion and regenerate 15% HP regen.","effects":[],"hitType":0,"iconIndex":322,"message1":"","message2":"","mpCost":0,"name":"I will stand up for you!","note":"<Cooldown: 10>\n<Instant Cast>\n\n<Whole action>\nadd state 37: user\n</Whole action>","occasion":1,"repeats":1,"requiredWtypeId1":0,"requiredWtypeId2":0,"scope":11,"speed":1,"stypeId":1,"successRate":100,"tpCost":0,"tpGain":0},
{"id":41,"animationId":0,"damage":{"critical":false,"elementId":0,"formula":"a.atk * 3","type":1,"variance":20},"description":"","effects":[{"code":12,"dataId":0,"value1":-0.5,"value2":0}],"hitType":0,"iconIndex":0,"message1":"","message2":"","mpCost":0,"name":"TDeek Ultimate","note":"","occasion":0,"repeats":1,"requiredWtypeId1":0,"requiredWtypeId2":0,"scope":2,"speed":0,"stypeId":1,"successRate":100,"tpCost":0,"tpGain":0},
{"id":42,"animationId":0,"damage":{"critical":false,"elementId":0,"formula":"a.atk * 1","type":1,"variance":20},"description":"","effects":[{"code":21,"dataId":21,"value1":1,"value2":0}],"hitType":0,"iconIndex":0,"message1":"","message2":"","mpCost":0,"name":"TMeat Ultimate","note":"<Whole action>\nadd state 32, 19: friends\n</Whole action>","occasion":0,"repeats":1,"requiredWtypeId1":0,"requiredWtypeId2":0,"scope":2,"speed":0,"stypeId":1,"successRate":100,"tpCost":0,"tpGain":0},
{"id":43,"animationId":0,"damage":{"critical":false,"elementId":0,"formula":"a.atk * 7","type":1,"variance":20},"description":"","effects":[{"code":21,"dataId":38,"value1":1,"value2":0}],"hitType":0,"iconIndex":64,"message1":"","message2":"","mpCost":0,"name":"Anko ultimate","note":"<Cooldown: 8>","occasion":0,"repeats":1,"requiredWtypeId1":0,"requiredWtypeId2":0,"scope":2,"speed":0,"stypeId":1,"successRate":100,"tpCost":0,"tpGain":0},
{"id":44,"animationId":0,"damage":{"critical":false,"elementId":0,"formula":"0","type":0,"variance":20},"description":"","effects":[{"code":21,"dataId":16,"value1":1,"value2":0},{"code":21,"dataId":32,"value1":1,"value2":0}],"hitType":0,"iconIndex":0,"message1":"","message2":"","mpCost":0,"name":"Eat dangos","note":"<Cooldown: 4>","occasion":0,"repeats":1,"requiredWtypeId1":0,"requiredWtypeId2":0,"scope":11,"speed":0,"stypeId":1,"successRate":100,"tpCost":0,"tpGain":0},
{"id":45,"animationId":0,"damage":{"critical":true,"elementId":0,"formula":"a.atk * 4","type":1,"variance":20},"description":"","effects":[{"code":21,"dataId":39,"value1":0.25,"value2":0}],"hitType":1,"iconIndex":77,"message1":"","message2":"","mpCost":0,"name":"Attack Tsu","note":"<HP Life Steal: 45%>","occasion":0,"repeats":1,"requiredWtypeId1":0,"requiredWtypeId2":0,"scope":1,"speed":0,"stypeId":1,"successRate":100,"tpCost":0,"tpGain":0},
{"id":46,"animationId":0,"damage":{"critical":true,"elementId":0,"formula":"a.atk * 10","type":1,"variance":35},"description":"Nuke 1 enemigo","effects":[],"hitType":0,"iconIndex":78,"message1":"","message2":"","mpCost":0,"name":"Ult 1","note":"<Cooldown: 6>","occasion":0,"repeats":1,"requiredWtypeId1":0,"requiredWtypeId2":0,"scope":1,"speed":0,"stypeId":1,"successRate":100,"tpCost":0,"tpGain":0},
{"id":47,"animationId":0,"damage":{"critical":true,"elementId":0,"formula":"a.atk * 5","type":1,"variance":80},"description":"Limpia todos los debuff, low regen 2 turnos y hace daño en area","effects":[],"hitType":0,"iconIndex":0,"message1":"","message2":"","mpCost":0,"name":"Ult 2 Summon attack","note":"<Cooldown: 8>","occasion":0,"repeats":1,"requiredWtypeId1":0,"requiredWtypeId2":0,"scope":1,"speed":0,"stypeId":1,"successRate":100,"tpCost":0,"tpGain":0},
{"id":48,"animationId":0,"damage":{"critical":true,"elementId":0,"formula":"a.atk * 3","type":1,"variance":100},"description":"Strong hit directly to the face.\n[50% Bleed] [35% Armor pen] [30% Crit chance]","effects":[{"code":21,"dataId":24,"value1":0.5,"value2":0}],"hitType":1,"iconIndex":106,"message1":"","message2":"","mpCost":20,"name":"Rage punch","note":"<Cooldown: 3>\n<Critical Rate: 30%>\n<Armor Penetration: 35%>\n","occasion":0,"repeats":1,"requiredWtypeId1":0,"requiredWtypeId2":0,"scope":1,"speed":0,"stypeId":1,"successRate":100,"tpCost":0,"tpGain":0},
{"id":49,"animationId":0,"damage":{"critical":false,"elementId":0,"formula":"0","type":0,"variance":20},"description":"","effects":[],"hitType":0,"iconIndex":0,"message1":"","message2":"","mpCost":0,"name":"","note":"","occasion":0,"repeats":1,"requiredWtypeId1":0,"requiredWtypeId2":0,"scope":1,"speed":0,"stypeId":1,"successRate":100,"tpCost":0,"tpGain":0},
{"id":50,"animationId":0,"damage":{"critical":false,"elementId":0,"formula":"0","type":0,"variance":20},"description":"","effects":[],"hitType":0,"iconIndex":0,"message1":"","message2":"","mpCost":0,"name":"","note":"","occasion":0,"repeats":1,"requiredWtypeId1":0,"requiredWtypeId2":0,"scope":1,"speed":0,"stypeId":1,"successRate":100,"tpCost":0,"tpGain":0},
{"id":51,"animationId":0,"damage":{"critical":false,"elementId":0,"formula":"0","type":0,"variance":20},"description":"","effects":[],"hitType":0,"iconIndex":0,"message1":"","message2":"","mpCost":0,"name":"","note":"","occasion":0,"repeats":1,"requiredWtypeId1":0,"requiredWtypeId2":0,"scope":1,"speed":0,"stypeId":1,"successRate":100,"tpCost":0,"tpGain":0},
{"id":52,"animationId":0,"damage":{"critical":false,"elementId":0,"formula":"0","type":0,"variance":20},"description":"","effects":[],"hitType":0,"iconIndex":0,"message1":"","message2":"","mpCost":0,"name":"","note":"","occasion":0,"repeats":1,"requiredWtypeId1":0,"requiredWtypeId2":0,"scope":1,"speed":0,"stypeId":1,"successRate":100,"tpCost":0,"tpGain":0},
{"id":53,"animationId":0,"damage":{"critical":false,"elementId":0,"formula":"0","type":0,"variance":20},"description":"","effects":[],"hitType":0,"iconIndex":0,"message1":"","message2":"","mpCost":0,"name":"","note":"","occasion":0,"repeats":1,"requiredWtypeId1":0,"requiredWtypeId2":0,"scope":1,"speed":0,"stypeId":1,"successRate":100,"tpCost":0,"tpGain":0},
{"id":54,"animationId":0,"damage":{"critical":false,"elementId":0,"formula":"0","type":0,"variance":20},"description":"","effects":[],"hitType":0,"iconIndex":0,"message1":"","message2":"","mpCost":0,"name":"","note":"","occasion":0,"repeats":1,"requiredWtypeId1":0,"requiredWtypeId2":0,"scope":1,"speed":0,"stypeId":1,"successRate":100,"tpCost":0,"tpGain":0},
{"id":55,"animationId":0,"damage":{"critical":false,"elementId":0,"formula":"0","type":0,"variance":20},"description":"","effects":[],"hitType":0,"iconIndex":0,"message1":"","message2":"","mpCost":0,"name":"","note":"","occasion":0,"repeats":1,"requiredWtypeId1":0,"requiredWtypeId2":0,"scope":1,"speed":0,"stypeId":1,"successRate":100,"tpCost":0,"tpGain":0},
{"id":56,"animationId":-1,"damage":{"critical":false,"elementId":-1,"formula":"a.atk * 2","type":1,"variance":20},"description":"","effects":[],"hitType":1,"iconIndex":334,"message1":" ¡ataca!","message2":"","mpCost":0,"name":"Harassment","note":"<Cooldown: 4>\n<HP Life Steal: 5%>","occasion":1,"repeats":1,"requiredWtypeId1":0,"requiredWtypeId2":0,"scope":5,"speed":0,"stypeId":0,"successRate":100,"tpCost":0,"tpGain":4},
{"id":57,"animationId":0,"damage":{"critical":false,"elementId":0,"formula":"0","type":0,"variance":20},"description":"","effects":[{"code":21,"dataId":42,"value1":1,"value2":0}],"hitType":0,"iconIndex":0,"message1":"","message2":"","mpCost":0,"name":"Prepare 3 Turns","note":"<Warmup: 5>\n<Cooldown: 15>\n<Target Barrier: +15>\n","occasion":0,"repeats":1,"requiredWtypeId1":0,"requiredWtypeId2":0,"scope":11,"speed":-2000,"stypeId":1,"successRate":100,"tpCost":0,"tpGain":0},
{"id":58,"animationId":0,"damage":{"critical":false,"elementId":0,"formula":"0","type":0,"variance":20},"description":"","effects":[{"code":22,"dataId":42,"value1":1,"value2":0},{"code":21,"dataId":43,"value1":1,"value2":0}],"hitType":0,"iconIndex":0,"message1":"","message2":"","mpCost":0,"name":"Prepare 2 Turns","note":"<Cooldown: 15>\n<Target Barrier: +15>\n<Warmup: 5>","occasion":0,"repeats":1,"requiredWtypeId1":0,"requiredWtypeId2":0,"scope":11,"speed":-2000,"stypeId":1,"successRate":100,"tpCost":0,"tpGain":0},
{"id":59,"animationId":0,"damage":{"critical":false,"elementId":0,"formula":"a.atk * 4","type":1,"variance":20},"description":"","effects":[{"code":21,"dataId":22,"value1":1,"value2":0}],"hitType":0,"iconIndex":343,"message1":"","message2":"","mpCost":0,"name":"Burn","note":"<Cooldown: 3>","occasion":0,"repeats":1,"requiredWtypeId1":0,"requiredWtypeId2":0,"scope":2,"speed":0,"stypeId":1,"successRate":100,"tpCost":0,"tpGain":0},
{"id":60,"animationId":0,"damage":{"critical":false,"elementId":0,"formula":"0","type":0,"variance":20},"description":"Recharge 60% of total user's chakra.","effects":[{"code":12,"dataId":0,"value1":0.75,"value2":0}],"hitType":0,"iconIndex":328,"message1":"","message2":"","mpCost":0,"name":"Charge chakra","note":"<Warmup: 2>\n<Cooldown: 7>\n\n<Target action>\nmotion chant: user\nanimation 52: user\naction effect: user\n</Target action>","occasion":1,"repeats":1,"requiredWtypeId1":0,"requiredWtypeId2":0,"scope":11,"speed":1,"stypeId":1,"successRate":100,"tpCost":0,"tpGain":0},
{"id":61,"animationId":0,"damage":{"critical":false,"elementId":0,"formula":"a.atk * 3","type":1,"variance":20},"description":"","effects":[],"hitType":1,"iconIndex":299,"message1":"","message2":"","mpCost":0,"name":"Cataclysm","note":"<Warmup: 5>\n<Cooldown: 15>\n<Action Cutin>","occasion":0,"repeats":1,"requiredWtypeId1":0,"requiredWtypeId2":0,"scope":6,"speed":0,"stypeId":1,"successRate":100,"tpCost":0,"tpGain":0},
{"id":62,"animationId":0,"damage":{"critical":false,"elementId":0,"formula":"a.atk * 3","type":1,"variance":20},"description":"veneno y debuff en area","effects":[],"hitType":0,"iconIndex":150,"message1":"","message2":"","mpCost":0,"name":"Gamabunta","note":"","occasion":1,"repeats":1,"requiredWtypeId1":0,"requiredWtypeId2":0,"scope":2,"speed":0,"stypeId":1,"successRate":100,"tpCost":0,"tpGain":0},
{"id":63,"animationId":0,"damage":{"critical":false,"elementId":0,"formula":"a.atk * 3","type":1,"variance":20},"description":"[I.C] You need to have kunai in your inventory.\n[30% Bleed] [Strengh scale]","effects":[{"code":21,"dataId":22,"value1":0.15,"value2":0}],"hitType":1,"iconIndex":294,"message1":"","message2":"","mpCost":0,"name":"Kunai storm","note":"<Cooldown: 7>\n\n<Armor Penetration: 30%>\n<Critical Rate: 20%>","occasion":0,"repeats":1,"requiredWtypeId1":0,"requiredWtypeId2":0,"scope":6,"speed":0,"stypeId":1,"successRate":100,"tpCost":0,"tpGain":0},
{"id":64,"animationId":0,"damage":{"critical":false,"elementId":0,"formula":"0","type":0,"variance":20},"description":"","effects":[],"hitType":0,"iconIndex":292,"message1":"","message2":"","mpCost":0,"name":"Shadow clones","note":"<Cooldown: 10>\n<Instant Cast>\n<Target action>\ncommon event: 25\n</Target action>","occasion":0,"repeats":1,"requiredWtypeId1":0,"requiredWtypeId2":0,"scope":1,"speed":0,"stypeId":1,"successRate":100,"tpCost":0,"tpGain":0},
{"id":65,"animationId":0,"damage":{"critical":false,"elementId":0,"formula":"a.atk * 3","type":1,"variance":20},"description":"","effects":[],"hitType":1,"iconIndex":339,"message1":"","message2":"","mpCost":0,"name":"Dance of shadows","note":"<HP Life Steal: 30%>\n\n<Cooldown: 10>","occasion":0,"repeats":1,"requiredWtypeId1":0,"requiredWtypeId2":0,"scope":6,"speed":0,"stypeId":1,"successRate":100,"tpCost":0,"tpGain":0},
{"id":66,"animationId":0,"damage":{"critical":false,"elementId":0,"formula":"a.mat * 3","type":1,"variance":50},"description":"","effects":[{"code":21,"dataId":47,"value1":1,"value2":0}],"hitType":2,"iconIndex":288,"message1":"","message2":"","mpCost":0,"name":"You didn't see it coming","note":"<Cooldown: 6>\n<Armor Penetration: 30%>\n<Critical Rate: 20%>","occasion":0,"repeats":1,"requiredWtypeId1":0,"requiredWtypeId2":0,"scope":6,"speed":0,"stypeId":1,"successRate":100,"tpCost":0,"tpGain":0},
{"id":67,"animationId":53,"damage":{"critical":false,"elementId":0,"formula":"0","type":0,"variance":20},"description":"Put 230 points of barrier.","effects":[],"hitType":0,"iconIndex":325,"message1":"","message2":"","mpCost":75,"name":"Strong barrier","note":"<Cooldown: 5>\n<Instant cast>\n\n<Target Barrier: +230>\n","occasion":0,"repeats":1,"requiredWtypeId1":0,"requiredWtypeId2":0,"scope":7,"speed":0,"stypeId":1,"successRate":100,"tpCost":0,"tpGain":0},
{"id":68,"animationId":0,"damage":{"critical":false,"elementId":0,"formula":"a.atk * 2.5","type":1,"variance":20},"description":"[I.C] You need to have kunai in your inventory.\n[30% Bleed] [Strengh scale]","effects":[{"code":21,"dataId":22,"value1":0.3,"value2":0}],"hitType":1,"iconIndex":347,"message1":"","message2":"","mpCost":0,"name":"Throw Kunai","note":"<Item Cost: 1 Kunais>\n<Cooldown: 5>\n<Armor Penetration: 30%>\n<Critical Rate: 20%>\n<Instant Cast>","occasion":0,"repeats":1,"requiredWtypeId1":0,"requiredWtypeId2":0,"scope":1,"speed":0,"stypeId":1,"successRate":100,"tpCost":0,"tpGain":0},
{"id":69,"animationId":51,"damage":{"critical":false,"elementId":0,"formula":"0","type":0,"variance":20},"description":"Increases the attack and defense of the party (Medium)\n[I.C]","effects":[{"code":21,"dataId":19,"value1":1,"value2":0},{"code":21,"dataId":20,"value1":1,"value2":0}],"hitType":0,"iconIndex":326,"message1":"","message2":"","mpCost":65,"name":"Strong buff","note":"<Cooldown: 4>\n<Instant Cast>","occasion":0,"repeats":1,"requiredWtypeId1":0,"requiredWtypeId2":0,"scope":8,"speed":0,"stypeId":1,"successRate":100,"tpCost":0,"tpGain":0},
{"id":70,"animationId":-1,"damage":{"critical":false,"elementId":-1,"formula":"a.atk * 3","type":1,"variance":20},"description":"","effects":[],"hitType":1,"iconIndex":334,"message1":" ¡ataca!","message2":"","mpCost":0,"name":"Harassment","note":"<Cooldown: 4>\n<Armor Penetration: 15%>\n<HP Life Steal: 45%>","occasion":1,"repeats":1,"requiredWtypeId1":0,"requiredWtypeId2":0,"scope":5,"speed":0,"stypeId":0,"successRate":100,"tpCost":0,"tpGain":4},
{"id":71,"animationId":0,"damage":{"critical":false,"elementId":0,"formula":"0","type":0,"variance":20},"description":"","effects":[],"hitType":0,"iconIndex":0,"message1":"","message2":"","mpCost":0,"name":"","note":"","occasion":0,"repeats":1,"requiredWtypeId1":0,"requiredWtypeId2":0,"scope":1,"speed":0,"stypeId":1,"successRate":100,"tpCost":0,"tpGain":0},
{"id":72,"animationId":0,"damage":{"critical":false,"elementId":0,"formula":"a.atk * 6","type":1,"variance":20},"description":"","effects":[{"code":22,"dataId":4,"value1":1,"value2":0},{"code":22,"dataId":5,"value1":1,"value2":0},{"code":22,"dataId":6,"value1":1,"value2":0},{"code":22,"dataId":23,"value1":1,"value2":0},{"code":22,"dataId":24,"value1":1,"value2":0},{"code":21,"dataId":32,"value1":1,"value2":0}],"hitType":1,"iconIndex":64,"message1":"","message2":"","mpCost":0,"name":"Third Gate OpenBK","note":"<After battle Cooldown: -99>\n<Armor Penetration: 20%>\n<Cooldown: 99>\n<Instant Cast>\n<HP Cost: 30%>\n<Action Cutin>\n\n<Target action>\nmotion skill: user\nwait for animation\nmotion abnormal: user\nwait for animation\ncamera focus: user\nzoom: 200%, 60\nwait for zoom\ncommon event: 19\nmotion missile: user\nmove user: target, front, 1\nwait for animation\nshake screen: 9, 9, 10\naction effect: target\naction effect: target\nanimation 92: target\nreset camera: 20\nreset zoom: 20\n</Target action>","occasion":1,"repeats":1,"requiredWtypeId1":0,"requiredWtypeId2":0,"scope":1,"speed":0,"stypeId":1,"successRate":100,"tpCost":0,"tpGain":0},
{"id":73,"animationId":0,"damage":{"critical":false,"elementId":0,"formula":"0","type":0,"variance":20},"description":"","effects":[],"hitType":0,"iconIndex":0,"message1":"","message2":"","mpCost":0,"name":"","note":"","occasion":0,"repeats":1,"requiredWtypeId1":0,"requiredWtypeId2":0,"scope":1,"speed":0,"stypeId":1,"successRate":100,"tpCost":0,"tpGain":0},
{"id":74,"animationId":53,"damage":{"critical":false,"elementId":0,"formula":"0","type":0,"variance":20},"description":"Refleja daño","effects":[{"code":21,"dataId":54,"value1":1,"value2":0}],"hitType":0,"iconIndex":0,"message1":"","message2":"","mpCost":0,"name":"Deidar Thorn","note":"<Cooldown: 7>\n<Instant Cast>\n<Target Barrier: +100>","occasion":0,"repeats":1,"requiredWtypeId1":0,"requiredWtypeId2":0,"scope":11,"speed":0,"stypeId":1,"successRate":100,"tpCost":0,"tpGain":0},
{"id":75,"animationId":0,"damage":{"critical":false,"elementId":0,"formula":"a.mat * 2.5","type":1,"variance":20},"description":"Ultimate daño en area, DRAGON","effects":[{"code":21,"dataId":38,"value1":0.5,"value2":0}],"hitType":2,"iconIndex":0,"message1":"","message2":"","mpCost":0,"name":"Shi Suri","note":"<Action Cutin>\n<Cooldown: 8>\n<Armor Penetration: 15%>\n\n<Target action>\nHIDE BATTLE HUD\ncommon event: 47\nanimation 32: target\naction effect: opponents\nSHOW BATTLE HUD\n</Target action>","occasion":0,"repeats":1,"requiredWtypeId1":0,"requiredWtypeId2":0,"scope":1,"speed":0,"stypeId":1,"successRate":100,"tpCost":0,"tpGain":0},
{"id":76,"animationId":3,"damage":{"critical":false,"elementId":0,"formula":"a.mat * 3","type":1,"variance":20},"description":"Ataque singular, DRAGON y a pie, mete slow y quemadura","effects":[{"code":21,"dataId":38,"value1":0.5,"value2":0}],"hitType":2,"iconIndex":0,"message1":"","message2":"","mpCost":0,"name":"C2","note":"<Cooldown: 6>\n<Armor Penetration: 25%>","occasion":0,"repeats":1,"requiredWtypeId1":0,"requiredWtypeId2":0,"scope":1,"speed":0,"stypeId":1,"successRate":100,"tpCost":0,"tpGain":0},
{"id":77,"animationId":107,"damage":{"critical":false,"elementId":0,"formula":"a.mat * 1","type":1,"variance":20},"description":"Daño en area, bajo","effects":[{"code":21,"dataId":38,"value1":0.1,"value2":0}],"hitType":2,"iconIndex":0,"message1":"","message2":"","mpCost":0,"name":"Attack D","note":"","occasion":0,"repeats":1,"requiredWtypeId1":0,"requiredWtypeId2":0,"scope":2,"speed":0,"stypeId":1,"successRate":100,"tpCost":0,"tpGain":0},
{"id":78,"animationId":0,"damage":{"critical":false,"elementId":0,"formula":"0","type":0,"variance":20},"description":"","effects":[],"hitType":0,"iconIndex":0,"message1":"","message2":"","mpCost":0,"name":"","note":"","occasion":0,"repeats":1,"requiredWtypeId1":0,"requiredWtypeId2":0,"scope":1,"speed":0,"stypeId":1,"successRate":100,"tpCost":0,"tpGain":0},
{"id":79,"animationId":0,"damage":{"critical":false,"elementId":0,"formula":"0","type":0,"variance":20},"description":"","effects":[],"hitType":0,"iconIndex":0,"message1":"","message2":"","mpCost":0,"name":"","note":"","occasion":0,"repeats":1,"requiredWtypeId1":0,"requiredWtypeId2":0,"scope":1,"speed":0,"stypeId":1,"successRate":100,"tpCost":0,"tpGain":0},
{"id":80,"animationId":0,"damage":{"critical":false,"elementId":0,"formula":"0","type":0,"variance":20},"description":"Invoca c4, A PIE,","effects":[],"hitType":0,"iconIndex":89,"message1":"","message2":"","mpCost":0,"name":"Clay creation","note":"<Cooldown: 5>\n<Instant Cast>\n<Target action>\ncommon event: 30\nanimation 117: user\n</Target action>","occasion":0,"repeats":1,"requiredWtypeId1":0,"requiredWtypeId2":0,"scope":1,"speed":0,"stypeId":1,"successRate":100,"tpCost":0,"tpGain":0},
{"id":81,"animationId":44,"damage":{"critical":false,"elementId":0,"formula":"0","type":0,"variance":20},"description":"Velocidad y un poquito de escudo","effects":[{"code":21,"dataId":32,"value1":1,"value2":0}],"hitType":0,"iconIndex":0,"message1":"","message2":"","mpCost":0,"name":"Buff D","note":"<Cooldown: 5>\n<Target Barrier: +100>","occasion":0,"repeats":1,"requiredWtypeId1":0,"requiredWtypeId2":0,"scope":8,"speed":0,"stypeId":1,"successRate":100,"tpCost":0,"tpGain":0},
{"id":82,"animationId":66,"damage":{"critical":false,"elementId":0,"formula":"a.mat * 2","type":1,"variance":20},"description":"","effects":[],"hitType":2,"iconIndex":0,"message1":"","message2":"","mpCost":0,"name":"Nendo ningyo","note":"<Action Cutin>\n<Cooldown: 8>\n<Armor Penetration: 15%>","occasion":0,"repeats":1,"requiredWtypeId1":0,"requiredWtypeId2":0,"scope":1,"speed":0,"stypeId":1,"successRate":100,"tpCost":0,"tpGain":0},
{"id":83,"animationId":0,"damage":{"critical":false,"elementId":0,"formula":"0","type":0,"variance":20},"description":"","effects":[],"hitType":0,"iconIndex":0,"message1":"","message2":"","mpCost":0,"name":"","note":"","occasion":0,"repeats":1,"requiredWtypeId1":0,"requiredWtypeId2":0,"scope":1,"speed":0,"stypeId":1,"successRate":100,"tpCost":0,"tpGain":0},
{"id":84,"animationId":120,"damage":{"critical":false,"elementId":0,"formula":"0","type":0,"variance":20},"description":"","effects":[{"code":22,"dataId":42,"value1":1,"value2":0},{"code":21,"dataId":43,"value1":1,"value2":0}],"hitType":0,"iconIndex":0,"message1":"","message2":"","mpCost":0,"name":"Prepare 2 Turns C","note":"<Cooldown: 15>\n<Target Barrier: +50>","occasion":0,"repeats":1,"requiredWtypeId1":0,"requiredWtypeId2":0,"scope":11,"speed":-2000,"stypeId":1,"successRate":100,"tpCost":0,"tpGain":0},
{"id":85,"animationId":120,"damage":{"critical":false,"elementId":0,"formula":"0","type":0,"variance":20},"description":"","effects":[{"code":21,"dataId":42,"value1":1,"value2":0}],"hitType":0,"iconIndex":0,"message1":"","message2":"","mpCost":0,"name":"Prepare 3 Turns C","note":"<Cooldown: 15>\n<Target Barrier: +50>","occasion":0,"repeats":1,"requiredWtypeId1":0,"requiredWtypeId2":0,"scope":11,"speed":-2000,"stypeId":1,"successRate":100,"tpCost":0,"tpGain":0},
{"id":86,"animationId":0,"damage":{"critical":true,"elementId":0,"formula":"a.setHp(0); a.performCollapse(); a.mat * 3.5","type":1,"variance":20},"description":"","effects":[],"hitType":0,"iconIndex":0,"message1":"","message2":"","mpCost":0,"name":"KATSU!","note":"<Action Cutin>\n<Armor Penetration: 35%>\n<Target Action>\nHIDE BATTLE HUD\nmove user: target, front, 10\nwait for movement\nwait: 20\ncommon event: 45\nanimation 109: user\naction effect: opponents\naction effect: opponents\naction effect: opponents\naction effect: opponents\nSHOW BATTLE HUD\n</Target Action>","occasion":1,"repeats":1,"requiredWtypeId1":0,"requiredWtypeId2":0,"scope":1,"speed":1,"stypeId":1,"successRate":100,"tpCost":0,"tpGain":0},
{"id":87,"animationId":0,"damage":{"critical":true,"elementId":0,"formula":"a.setHp(0); a.performCollapse(); a.mat * 6","type":1,"variance":70},"description":"","effects":[{"code":21,"dataId":38,"value1":0.35,"value2":0}],"hitType":2,"iconIndex":0,"message1":"","message2":"","mpCost":0,"name":"C3","note":"<Warmup: 1>\n<Target Action>\nmove user: target, front, 1\nwait for movement\nwait: 20\nanimation 107: user\naction effect: opponents\n</Target Action>","occasion":1,"repeats":1,"requiredWtypeId1":0,"requiredWtypeId2":0,"scope":4,"speed":1,"stypeId":1,"successRate":100,"tpCost":0,"tpGain":0},
{"id":88,"animationId":0,"damage":{"critical":true,"elementId":0,"formula":"a.setHp(0); a.performCollapse(); a.mat * 3","type":1,"variance":70},"description":"","effects":[{"code":21,"dataId":38,"value1":0.35,"value2":0}],"hitType":2,"iconIndex":83,"message1":"","message2":"","mpCost":0,"name":"C1","note":"<Warmup: 1>\n<Armor Penetration: 25%>\n<Target Action>\nmove user: target, front, 1\nwait for movement\nwait: 20\nanimation 66: user\naction effect: opponents\n</Target Action>","occasion":1,"repeats":1,"requiredWtypeId1":0,"requiredWtypeId2":0,"scope":1,"speed":1,"stypeId":1,"successRate":100,"tpCost":0,"tpGain":0},
{"id":89,"animationId":120,"damage":{"critical":false,"elementId":0,"formula":"0","type":0,"variance":20},"description":"","effects":[{"code":22,"dataId":42,"value1":1,"value2":0},{"code":21,"dataId":43,"value1":1,"value2":0},{"code":21,"dataId":32,"value1":1,"value2":0}],"hitType":0,"iconIndex":0,"message1":"","message2":"","mpCost":0,"name":"Prepare","note":"<Cooldown: 2>\n<Target Barrier: +50>","occasion":0,"repeats":1,"requiredWtypeId1":0,"requiredWtypeId2":0,"scope":11,"speed":-2000,"stypeId":1,"successRate":100,"tpCost":0,"tpGain":0},
{"id":90,"animationId":0,"damage":{"critical":false,"elementId":0,"formula":"0","type":0,"variance":20},"description":"","effects":[],"hitType":0,"iconIndex":0,"message1":"","message2":"","mpCost":0,"name":"","note":"","occasion":0,"repeats":1,"requiredWtypeId1":0,"requiredWtypeId2":0,"scope":1,"speed":0,"stypeId":1,"successRate":100,"tpCost":0,"tpGain":0},
{"id":91,"animationId":107,"damage":{"critical":false,"elementId":0,"formula":"a.mat * 4.5","type":1,"variance":20},"description":"Daño en area, bajo","effects":[],"hitType":2,"iconIndex":0,"message1":"","message2":"","mpCost":0,"name":"Dmg area","note":"<Cooldown: 7>\n<Armor Penetration: 15%>","occasion":0,"repeats":1,"requiredWtypeId1":0,"requiredWtypeId2":0,"scope":2,"speed":0,"stypeId":1,"successRate":100,"tpCost":0,"tpGain":0},
{"id":92,"animationId":0,"damage":{"critical":false,"elementId":0,"formula":"a.atk * 4.5","type":1,"variance":20},"description":"","effects":[],"hitType":1,"iconIndex":0,"message1":"","message2":"","mpCost":0,"name":"Dmg assasin","note":"<HP Life Steal: 30%>\n<Cooldown: 3>\n<Armor Penetration: 15%>","occasion":0,"repeats":1,"requiredWtypeId1":0,"requiredWtypeId2":0,"scope":6,"speed":0,"stypeId":1,"successRate":100,"tpCost":0,"tpGain":0},
{"id":93,"animationId":0,"damage":{"critical":false,"elementId":0,"formula":"a.atk * 6","type":1,"variance":20},"description":"","effects":[],"hitType":1,"iconIndex":299,"message1":"","message2":"","mpCost":0,"name":"Cataclysm LVL 2","note":"<Cooldown: 7>\n<Armor Penetration: 15%>","occasion":0,"repeats":1,"requiredWtypeId1":0,"requiredWtypeId2":0,"scope":6,"speed":0,"stypeId":1,"successRate":100,"tpCost":0,"tpGain":0},
{"id":94,"animationId":0,"damage":{"critical":true,"elementId":0,"formula":"a.mat * 999999999","type":1,"variance":20},"description":"[I.Cast] You try to distract the enemy.\n[75% Attack down] [5% Stun] [5% Confusion] [50% Love] [I.C]","effects":[],"hitType":0,"iconIndex":298,"message1":"","message2":"","mpCost":0,"name":"Harem no jutsu B","note":"<Cooldown: 7>\n\n<Whole Action>\nHIDE BATTLE HUD\nmotion chant: user\ncommon event: 20\nanimation 33: user\nwait for animation\nSHOW BATTLE HUD\n</Whole action>","occasion":1,"repeats":1,"requiredWtypeId1":0,"requiredWtypeId2":0,"scope":1,"speed":0,"stypeId":1,"successRate":100,"tpCost":0,"tpGain":0},
{"id":95,"animationId":0,"damage":{"critical":false,"elementId":0,"formula":"0","type":0,"variance":20},"description":"","effects":[],"hitType":0,"iconIndex":0,"message1":"","message2":"","mpCost":0,"name":"","note":"","occasion":0,"repeats":1,"requiredWtypeId1":0,"requiredWtypeId2":0,"scope":1,"speed":0,"stypeId":1,"successRate":100,"tpCost":0,"tpGain":0},
{"id":96,"animationId":0,"damage":{"critical":false,"elementId":0,"formula":"0","type":0,"variance":20},"description":"","effects":[],"hitType":0,"iconIndex":0,"message1":"","message2":"","mpCost":0,"name":"","note":"","occasion":0,"repeats":1,"requiredWtypeId1":0,"requiredWtypeId2":0,"scope":1,"speed":0,"stypeId":1,"successRate":100,"tpCost":0,"tpGain":0},
{"id":97,"animationId":0,"damage":{"critical":false,"elementId":0,"formula":"0","type":0,"variance":20},"description":"","effects":[],"hitType":0,"iconIndex":0,"message1":"","message2":"","mpCost":0,"name":"","note":"","occasion":0,"repeats":1,"requiredWtypeId1":0,"requiredWtypeId2":0,"scope":1,"speed":0,"stypeId":1,"successRate":100,"tpCost":0,"tpGain":0},
{"id":98,"animationId":0,"damage":{"critical":false,"elementId":0,"formula":"0","type":0,"variance":20},"description":"","effects":[],"hitType":0,"iconIndex":0,"message1":"","message2":"","mpCost":0,"name":"","note":"","occasion":0,"repeats":1,"requiredWtypeId1":0,"requiredWtypeId2":0,"scope":1,"speed":0,"stypeId":1,"successRate":100,"tpCost":0,"tpGain":0},
{"id":99,"animationId":0,"damage":{"critical":false,"elementId":0,"formula":"0","type":0,"variance":20},"description":"","effects":[],"hitType":0,"iconIndex":0,"message1":"","message2":"","mpCost":0,"name":"","note":"","occasion":0,"repeats":1,"requiredWtypeId1":0,"requiredWtypeId2":0,"scope":1,"speed":0,"stypeId":1,"successRate":100,"tpCost":0,"tpGain":0},
{"id":100,"animationId":0,"damage":{"critical":false,"elementId":0,"formula":"0","type":0,"variance":20},"description":"","effects":[],"hitType":0,"iconIndex":0,"message1":"","message2":"","mpCost":0,"name":"","note":"","occasion":0,"repeats":1,"requiredWtypeId1":0,"requiredWtypeId2":0,"scope":1,"speed":0,"stypeId":1,"successRate":100,"tpCost":0,"tpGain":0}
]